auto_retry/__init__.py
auto_retry/api.py
auto_retry/compat.py
auto_retry-2023.12.8.1.dist-info/LICENSE
auto_retry-2023.12.8.1.dist-info/METADATA
auto_retry-2023.12.8.1.dist-info/WHEEL
auto_retry-2023.12.8.1.dist-info/RECORD
