Metadata-Version: 2.1
Name: auto-retry
Version: 2023.12.8.1
Summary: 
Author: Arter Tendean
Author-email: arter.tendean.07@gmail.com
Requires-Python: >=3.8,<4.0
Classifier: Programming Language :: Python :: 3
Classifier: Programming Language :: Python :: 3.8
Classifier: Programming Language :: Python :: 3.9
Classifier: Programming Language :: Python :: 3.10
Classifier: Programming Language :: Python :: 3.11
Classifier: Programming Language :: Python :: 3.12
